[
	{"city": "dali", "name": "整租·兴泰小区西区 4室2厅 南/北", "district": "大理市", "street": "下关北区", "community": "兴泰小区西区", "price": 2000, "square": 123.0, "direction": "南 北", "layout": "4室2厅2卫"},
	{"city": "dali", "name": "整租·华辰玉海豪庭 3室2厅 南", "district": "大理市", "street": "下关北区", "community": "华辰玉海豪庭", "price": 2200, "square": 124.0, "direction": "南", "layout": "3室2厅2卫"},
	{"city": "dali", "name": "整租·汇宁豪品 3室2厅 西", "district": "大理市", "street": "下关北区", "community": "汇宁豪品", "price": 2500, "square": 105.0, "direction": "西", "layout": "3室2厅1卫"},
	{"city": "dali", "name": "整租·艺墅花乡 2室1厅 东", "district": "大理市", "street": "下关北区", "community": "艺墅花乡", "price": 1800, "square": 55.0, "direction": "东", "layout": "2室1厅1卫"},
	{"city": "dali", "name": "整租·兴泰小区西区 4室2厅 南/北", "district": "大理市", "street": "下关北区", "community": "兴泰小区西区", "price": 2000, "square": 123.0, "direction": "南 北", "layout": "4室2厅2卫"},
	{"city": "dali", "name": "整租·华辰玉海豪庭 3室2厅 南", "district": "大理市", "street": "下关北区", "community": "华辰玉海豪庭", "price": 2200, "square": 124.0, "direction": "南", "layout": "3室2厅2卫"},
	{"city": "dali", "name": "整租·汇宁豪品 3室2厅 西", "district": "大理市", "street": "下关北区", "community": "汇宁豪品", "price": 2500, "square": 105.0, "direction": "西", "layout": "3室2厅1卫"},
	{"city": "dali", "name": "整租·苹果城 3室2厅 南/北", "district": "大理市", "street": "下关北区", "community": "苹果城", "price": 2200, "square": 106.0, "direction": "南 北", "layout": "3室2厅1卫"},
	{"city": "dali", "name": "整租·大关邑村 2室1厅 西南", "district": "大理市", "street": "下关北区", "community": "大关邑村", "price": 1100, "square": 70.0, "direction": "西南", "layout": "2室1厅2卫"},
	{"city": "dali", "name": "整租·洱海庄园 3室2厅 南/北", "district": "大理市", "street": "下关北区", "community": "洱海庄园", "price": 2700, "square": 89.0, "direction": "南 北", "layout": "3室2厅1卫"},
	{"city": "dali", "name": "整租·俊发滨海俊园 1室1厅 南/北", "district": "大理市", "street": "市区", "community": "俊发滨海俊园", "price": 1800, "square": 51.0, "direction": "南 北", "layout": "1室1厅2卫"},
	{"city": "dali", "name": "整租·俊发滨海俊园 5室2厅 南/北", "district": "大理市", "street": "市区", "community": "俊发滨海俊园", "price": 9000, "square": 313.0, "direction": "南 北", "layout": "5室2厅4卫"},
	{"city": "dali", "name": "整租·天泰大理十畝 3室2厅 跃层 东", "district": "大理市", "street": "市区", "community": "天泰大理十畝", "price": 4600, "square": 86.0, "direction": "东", "layout": "3室2厅2卫"},
	{"city": "dali", "name": "整租·三江雅苑 4室2厅 南/北", "district": "大理市", "street": "市区", "community": "三江雅苑", "price": 2000, "square": 135.0, "direction": "南 北", "layout": "4室2厅2卫"},
	{"city": "dali", "name": "整租·洱海天域国际公寓 4室2厅 南/北", "district": "大理市", "street": "市区", "community": "洱海天域国际公寓", "price": 9500, "square": 224.0, "direction": "南 北", "layout": "4室2厅2卫"},
	{"city": "dali", "name": "整租·国税局小区 4室2厅 南/北", "district": "大理市", "street": "市区", "community": "国税局小区", "price": 1700, "square": 94.0, "direction": "南 北", "layout": "4室2厅2卫"},
	{"city": "dali", "name": "整租·俊发滨海俊园 1室1厅 南/北", "district": "大理市", "street": "市区", "community": "俊发滨海俊园", "price": 1800, "square": 51.0, "direction": "南 北", "layout": "1室1厅2卫"},
	{"city": "dali", "name": "整租·闲都 4室2厅 东/南/西/北", "district": "大理市", "street": "市区", "community": "闲都", "price": 6500, "square": 224.68, "direction": "东 南 西 北", "layout": "4室2厅3卫"},
	{"city": "dali", "name": "整租·正阳时代广场 1室1厅 北", "district": "大理市", "street": "市区", "community": "正阳时代广场", "price": 600, "square": 11.0, "direction": "北", "layout": "1室1厅1卫"},
	{"city": "dali", "name": "整租·水电宿舍三小小区 2室2厅 南/北", "district": "大理市", "street": "市区", "community": "水电宿舍三小小区", "price": 1300, "square": 76.76, "direction": "南 北", "layout": "2室2厅1卫"},
	{"city": "dali", "name": "整租·天泰大理十畝 5室2厅 南/北", "district": "大理市", "street": "市区", "community": "天泰大理十畝", "price": 3500, "square": 264.0, "direction": "南 北", "layout": "5室2厅4卫"},
	{"city": "dali", "name": "整租·万科·大理·拾叁月 4室2厅 南", "district": "大理市", "street": "满江片区", "community": "万科·大理·拾叁月", "price": 3800, "square": 143.0, "direction": "南", "layout": "4室2厅2卫"},
	{"city": "dali", "name": "整租·大理公馆 2室2厅 西北", "district": "大理市", "street": "满江片区", "community": "大理公馆", "price": 3200, "square": 89.0, "direction": "西北", "layout": "2室2厅1卫"},
	{"city": "dali", "name": "整租·五洲国际商贸城A区 1室0厅 北", "district": "大理市", "street": "满江片区", "community": "五洲国际商贸城A区", "price": 550, "square": 35.0, "direction": "北", "layout": "1室0厅1卫"},
	{"city": "dali", "name": "整租·万科·大理·拾叁月 3室2厅 西", "district": "大理市", "street": "满江片区", "community": "万科·大理·拾叁月", "price": 5500, "square": 133.0, "direction": "西", "layout": "3室2厅2卫"},
	{"city": "dali", "name": "整租·万科·大理·拾叁月 2室2厅 东南", "district": "大理市", "street": "满江片区", "community": "万科·大理·拾叁月", "price": 2500, "square": 86.0, "direction": "东南", "layout": "2室2厅1卫"},
	{"city": "dali", "name": "整租·云麓青城 3室2厅 东", "district": "大理市", "street": "满江片区", "community": "云麓青城", "price": 2200, "square": 119.0, "direction": "东", "layout": "3室2厅2卫"},
	{"city": "dali", "name": "整租·洱海龙湾 4室2厅 南/北", "district": "大理市", "street": "经开区", "community": "洱海龙湾", "price": 12000, "square": 340.0, "direction": "南 北", "layout": "4室2厅4卫"},
	{"city": "dali", "name": "整租·鑫源小区 3室2厅 南/北", "district": "大理市", "street": "经开区", "community": "鑫源小区", "price": 1800, "square": 108.29, "direction": "南 北", "layout": "3室2厅2卫"},
	{"city": "dali", "name": "整租·苍露园 3室2厅 南/北", "district": "大理市", "street": "经开区", "community": "苍露园", "price": 1600, "square": 89.25, "direction": "南 北", "layout": "3室2厅1卫"},
	{"city": "dali", "name": "整租·达人联盟 5室2厅 跃层 南", "district": "大理市", "street": "经开区", "community": "达人联盟", "price": 3600, "square": 135.0, "direction": "南", "layout": "5室2厅3卫"},
	{"city": "dali", "name": "整租·洱海天域 6室3厅 南/北", "district": "大理市", "street": "经开区", "community": "洱海天域", "price": 23000, "square": 280.0, "direction": "南 北", "layout": "6室3厅3卫"},
	{"city": "dali", "name": "整租·荣欣苑小区 5室2厅 跃层 南", "district": "大理市", "street": "经开区", "community": "荣欣苑小区", "price": 4500, "square": 184.81, "direction": "南", "layout": "5室2厅3卫"},
	{"city": "dali", "name": "整租·东岸和园 3室2厅 西北", "district": "大理市", "street": "海东", "community": "东岸和园", "price": 2000, "square": 131.61, "direction": "西北", "layout": "3室2厅2卫"},
	{"city": "dali", "name": "整租·东岸清园 1室1厅 西北", "district": "大理市", "street": "海东", "community": "东岸清园", "price": 1000, "square": 54.9, "direction": "西北", "layout": "1室1厅1卫"},
	{"city": "dali", "name": "整租·纳思海岸春天 2室2厅 西", "district": "大理市", "street": "海东", "community": "纳思海岸春天", "price": 1000, "square": 64.16, "direction": "西", "layout": "2室2厅1卫"},
	{"city": "dali", "name": "整租·纳思海岸春天 2室2厅 南", "district": "大理市", "street": "海东", "community": "纳思海岸春天", "price": 1100, "square": 64.0, "direction": "南", "layout": "2室2厅1卫"},
	{"city": "dali", "name": "整租·理想邦 9室3厅 南/北", "district": "大理市", "street": "海东", "community": "理想邦", "price": 34000, "square": 680.0, "direction": "南 北", "layout": "9室3厅9卫"},
	{"city": "dali", "name": "整租·东岸和园 3室2厅 西北", "district": "大理市", "street": "海东", "community": "东岸和园", "price": 2000, "square": 131.61, "direction": "西北", "layout": "3室2厅2卫"},
	{"city": "dali", "name": "整租·东岸清园 1室1厅 西北", "district": "大理市", "street": "海东", "community": "东岸清园", "price": 1000, "square": 54.9, "direction": "西北", "layout": "1室1厅1卫"},
	{"city": "dali", "name": "整租·纳思海岸春天 2室2厅 西", "district": "大理市", "street": "海东", "community": "纳思海岸春天", "price": 1000, "square": 64.16, "direction": "西", "layout": "2室2厅1卫"},
	{"city": "dali", "name": "整租·纳思海岸春天 2室2厅 南", "district": "大理市", "street": "海东", "community": "纳思海岸春天", "price": 1100, "square": 64.0, "direction": "南", "layout": "2室2厅1卫"},
	{"city": "dali", "name": "整租·理想邦 9室3厅 南/北", "district": "大理市", "street": "海东", "community": "理想邦", "price": 34000, "square": 680.0, "direction": "南 北", "layout": "9室3厅9卫"},
	{"city": "dali", "name": "整租·大理阳光 3室2厅 西南/东北", "district": "大理市", "street": "海东", "community": "大理阳光", "price": 2500, "square": 158.0, "direction": "西南 东北", "layout": "3室2厅2卫"},
	{"city": "dali", "name": "整租·南五里桥 7室1厅 南", "district": "大理市", "street": "古城", "community": "南五里桥", "price": 6000, "square": 200.0, "direction": "南", "layout": "7室1厅8卫"},
	{"city": "dali", "name": "整租·大理的小院子北区 2室1厅 西", "district": "大理市", "street": "古城", "community": "大理的小院子北区", "price": 8000, "square": 65.21, "direction": "西", "layout": "2室1厅1卫"},
	{"city": "dali", "name": "整租·大理的小院子南区 3室1厅 跃层 东/东南/西", "district": "大理市", "street": "古城", "community": "大理的小院子南区", "price": 10000, "square": 179.89, "direction": "东 东南 西", "layout": "3室1厅4卫"},
	{"city": "dali", "name": "整租·大理的小院子南区 4室2厅 东/西", "district": "大理市", "street": "古城", "community": "大理的小院子南区", "price": 7500, "square": 156.0, "direction": "东 西", "layout": "4室2厅4卫"},
	{"city": "dali", "name": "整租·文献路 6室3厅 南/北", "district": "大理市", "street": "古城", "community": "文献路", "price": 10000, "square": 350.0, "direction": "南 北", "layout": "6室3厅5卫"},
	{"city": "dali", "name": "整租·大理的小院子中区 3室1厅 东/西", "district": "大理市", "street": "古城", "community": "大理的小院子中区", "price": 6500, "square": 119.27, "direction": "东 西", "layout": "3室1厅3卫"},
	{"city": "dali", "name": "整租·南五里桥 7室1厅 南", "district": "大理市", "street": "古城", "community": "南五里桥", "price": 6000, "square": 200.0, "direction": "南", "layout": "7室1厅8卫"},
	{"city": "dali", "name": "整租·大理的小院子北区 2室1厅 西", "district": "大理市", "street": "古城", "community": "大理的小院子北区", "price": 8000, "square": 65.21, "direction": "西", "layout": "2室1厅1卫"},
	{"city": "dali", "name": "整租·大理的小院子南区 3室1厅 跃层 东/东南/西", "district": "大理市", "street": "古城", "community": "大理的小院子南区", "price": 10000, "square": 179.89, "direction": "东 东南 西", "layout": "3室1厅4卫"},
	{"city": "dali", "name": "整租·大理的小院子南区 4室2厅 东/西", "district": "大理市", "street": "古城", "community": "大理的小院子南区", "price": 7500, "square": 156.0, "direction": "东 西", "layout": "4室2厅4卫"},
	{"city": "dali", "name": "整租·文献路 6室3厅 南/北", "district": "大理市", "street": "古城", "community": "文献路", "price": 10000, "square": 350.0, "direction": "南 北", "layout": "6室3厅5卫"},
	{"city": "dali", "name": "整租·大理慢谷-世界健康小镇 3室2厅 南/北", "district": "大理市", "street": "凤仪", "community": "大理慢谷-世界健康小镇", "price": 1600, "square": 87.0, "direction": "南 北", "layout": "3室2厅1卫"},
	{"city": "dali", "name": "整租·华洲龙康苑 2室2厅 东/西", "district": "大理市", "street": "凤仪", "community": "华洲龙康苑", "price": 1300, "square": 76.0, "direction": "东 西", "layout": "2室2厅1卫"},
	{"city": "dali", "name": "整租·大理慢谷-世界健康小镇 2室2厅 南/北", "district": "大理市", "street": "凤仪", "community": "大理慢谷-世界健康小镇", "price": 1500, "square": 87.0, "direction": "南 北", "layout": "2室2厅1卫"},
	{"city": "dali", "name": "整租·凤仪庄园 2室2厅 南/北", "district": "大理市", "street": "凤仪", "community": "凤仪庄园", "price": 1300, "square": 76.0, "direction": "南 北", "layout": "2室2厅1卫"},
	{"city": "dali", "name": "整租·凤仪庄园 3室2厅 南/北", "district": "大理市", "street": "凤仪", "community": "凤仪庄园", "price": 1600, "square": 96.0, "direction": "南 北", "layout": "3室2厅1卫"},
	{"city": "dali", "name": "整租·凤仪庄园 2室2厅 南/北", "district": "大理市", "street": "凤仪", "community": "凤仪庄园", "price": 1400, "square": 78.0, "direction": "南 北", "layout": "2室2厅1卫"},
	{"city": "dali", "name": "整租·凤仪庄园 3室2厅 南/北", "district": "大理市", "street": "凤仪", "community": "凤仪庄园", "price": 1300, "square": 96.0, "direction": "南 北", "layout": "3室2厅1卫"},
	{"city": "dali", "name": "整租·凤仪供电所宿舍 3室2厅 东/西", "district": "大理市", "street": "凤仪", "community": "凤仪供电所宿舍", "price": 1400, "square": 99.94, "direction": "东 西", "layout": "3室2厅1卫"},
	{"city": "dali", "name": "整租·大理慢谷-世界健康小镇 3室2厅 南/北", "district": "大理市", "street": "凤仪", "community": "大理慢谷-世界健康小镇", "price": 2500, "square": 84.0, "direction": "南 北", "layout": "3室2厅1卫"},
	{"city": "dali", "name": "整租·凤庭苑 3室2厅 东", "district": "大理市", "street": "凤仪", "community": "凤庭苑", "price": 1500, "square": 80.0, "direction": "东", "layout": "3室2厅1卫"},
	{"city": "dali", "name": "整租·大理慢谷-世界健康小镇 2室2厅 南", "district": "大理市", "street": "凤仪", "community": "大理慢谷-世界健康小镇", "price": 2300, "square": 91.5, "direction": "南", "layout": "2室2厅1卫"},
	{"city": "dali", "name": "整租·凤仪庄园 3室2厅 南/北", "district": "大理市", "street": "凤仪", "community": "凤仪庄园", "price": 1600, "square": 96.8, "direction": "南 北", "layout": "3室2厅1卫"},
	{"city": "dali", "name": "整租·荷花村 9室1厅 西南", "district": "大理市", "street": "下关北区", "community": "荷花村", "price": 6500, "square": 300.0, "direction": "西南", "layout": "9室1厅9卫"},
	{"city": "dali", "name": "整租·龙悦华府 3室2厅 南/北", "district": "大理市", "street": "下关北区", "community": "龙悦华府", "price": 2000, "square": 133.4, "direction": "南 北", "layout": "3室2厅2卫"},
	{"city": "dali", "name": "整租·洱滨村7组 9室3厅 东/西", "district": "大理市", "street": "下关北区", "community": "洱滨村7组", "price": 8400, "square": 376.0, "direction": "东 西", "layout": "9室3厅3卫"},
	{"city": "dali", "name": "整租·龙腾苑 3室2厅 南/北", "district": "大理市", "street": "下关北区", "community": "龙腾苑", "price": 1600, "square": 102.5, "direction": "南 北", "layout": "3室2厅2卫"},
	{"city": "dali", "name": "整租·惠丰瑞城 4室1厅 东/西", "district": "大理市", "street": "下关北区", "community": "惠丰瑞城", "price": 2000, "square": 128.0, "direction": "东 西", "layout": "4室1厅2卫"},
	{"city": "dali", "name": "整租·灵瑞小区 5室3厅 西", "district": "大理市", "street": "下关北区", "community": "灵瑞小区", "price": 10000, "square": 480.0, "direction": "西", "layout": "5室3厅3卫"},
	{"city": "dali", "name": "整租·山水清城小区 1室1厅 南", "district": "大理市", "street": "下关北区", "community": "山水清城小区", "price": 2300, "square": 30.0, "direction": "南", "layout": "1室1厅1卫"},
	{"city": "dali", "name": "整租·水电十四局宿舍 2室1厅 东", "district": "大理市", "street": "下关北区", "community": "水电十四局宿舍", "price": 1200, "square": 50.0, "direction": "东", "layout": "2室1厅1卫"},
	{"city": "dali", "name": "整租·水岸华府 4室2厅 南/北", "district": "大理市", "street": "下关北区", "community": "水岸华府", "price": 1200, "square": 162.8, "direction": "南 北", "layout": "4室2厅2卫"},
	{"city": "dali", "name": "整租·兴国路28号 2室2厅 南/北", "district": "大理市", "street": "下关北区", "community": "兴国路28号", "price": 1000, "square": 69.32, "direction": "南 北", "layout": "2室2厅1卫"},
	{"city": "dali", "name": "整租·新世纪花园 2室2厅 东", "district": "大理市", "street": "下关北区", "community": "新世纪花园", "price": 2700, "square": 89.0, "direction": "东", "layout": "2室2厅1卫"},
	{"city": "dali", "name": "整租·亚汇荔园 3室2厅 南", "district": "大理市", "street": "下关北区", "community": "亚汇荔园", "price": 2200, "square": 130.0, "direction": "南", "layout": "3室2厅2卫"},
	{"city": "dali", "name": "整租·龙悦华府 3室2厅 南", "district": "大理市", "street": "下关北区", "community": "龙悦华府", "price": 1800, "square": 119.0, "direction": "南", "layout": "3室2厅2卫"},
	{"city": "dali", "name": "整租·新世纪花园 3室2厅 南/北", "district": "大理市", "street": "下关北区", "community": "新世纪花园", "price": 2500, "square": 104.0, "direction": "南 北", "layout": "3室2厅2卫"},
	{"city": "dali", "name": "整租·惠丰瑞城 1室0厅 东", "district": "大理市", "street": "下关北区", "community": "惠丰瑞城", "price": 3200, "square": 60.0, "direction": "东", "layout": "1室0厅1卫"},
	{"city": "dali", "name": "整租·兴隆园小区大啤集团宿舍 3室2厅 东/西", "district": "大理市", "street": "下关北区", "community": "兴隆园小区大啤集团宿舍", "price": 1800, "square": 104.0, "direction": "东 西", "layout": "3室2厅2卫"},
	{"city": "dali", "name": "整租·兴隆园小区大啤集团宿舍 3室2厅 东/西", "district": "大理市", "street": "下关北区", "community": "兴隆园小区大啤集团宿舍", "price": 2000, "square": 96.0, "direction": "东 西", "layout": "3室2厅2卫"},
	{"city": "dali", "name": "整租·鸿园小区 3室1厅 东/南/西", "district": "大理市", "street": "下关北区", "community": "鸿园小区", "price": 2200, "square": 100.05, "direction": "东 南 西", "layout": "3室1厅2卫"},
	{"city": "dali", "name": "整租·新世纪花园 3室2厅 南/北", "district": "大理市", "street": "下关北区", "community": "新世纪花园", "price": 2900, "square": 104.0, "direction": "南 北", "layout": "3室2厅2卫"},
	{"city": "dali", "name": "整租·滇西水泥厂宿舍 3室1厅 东/西", "district": "大理市", "street": "下关北区", "community": "滇西水泥厂宿舍", "price": 1300, "square": 75.0, "direction": "东 西", "layout": "3室1厅1卫"},
	{"city": "dali", "name": "整租·艺墅花乡 2室1厅 南", "district": "大理市", "street": "下关北区", "community": "艺墅花乡", "price": 1700, "square": 66.0, "direction": "南", "layout": "2室1厅2卫"},
	{"city": "dali", "name": "整租·康典佳园 3室2厅 南/北", "district": "大理市", "street": "下关北区", "community": "康典佳园", "price": 2600, "square": 133.45, "direction": "南 北", "layout": "3室2厅2卫"},
	{"city": "dali", "name": "整租·建标玉风商住楼 1室1厅 东/西", "district": "大理市", "street": "下关北区", "community": "建标玉风商住楼", "price": 3000, "square": 64.34, "direction": "东 西", "layout": "1室1厅1卫"},
	{"city": "dali", "name": "整租·惠丰瑞城 2室2厅 东", "district": "大理市", "street": "下关北区", "community": "惠丰瑞城", "price": 2100, "square": 82.0, "direction": "东", "layout": "2室2厅1卫"},
	{"city": "dali", "name": "整租·金水楼台 4室2厅 南/北", "district": "大理市", "street": "下关北区", "community": "金水楼台", "price": 5500, "square": 200.0, "direction": "南 北", "layout": "4室2厅3卫"},
	{"city": "dali", "name": "整租·太和苑 3室2厅 东", "district": "大理市", "street": "下关北区", "community": "太和苑", "price": 1600, "square": 115.6, "direction": "东", "layout": "3室2厅2卫"},
	{"city": "dali", "name": "整租·山水丽都 3室2厅 南/北", "district": "大理市", "street": "市区", "community": "山水丽都", "price": 2000, "square": 140.0, "direction": "南 北", "layout": "3室2厅2卫"},
	{"city": "dali", "name": "整租·金龙巷 20室0厅 东南", "district": "大理市", "street": "市区", "community": "金龙巷", "price": 10000, "square": 780.0, "direction": "东南", "layout": "20室0厅9卫"},
	{"city": "dali", "name": "整租·洱海天域国际公寓 2室2厅 南", "district": "大理市", "street": "市区", "community": "洱海天域国际公寓", "price": 2000, "square": 89.0, "direction": "南", "layout": "2室2厅1卫"},
	{"city": "dali", "name": "整租·洱海天域国际公寓 3室2厅 南/北", "district": "大理市", "street": "市区", "community": "洱海天域国际公寓", "price": 3500, "square": 130.35, "direction": "南 北", "layout": "3室2厅2卫"},
	{"city": "dali", "name": "整租·锦达豪庭 3室2厅 南/北", "district": "大理市", "street": "市区", "community": "锦达豪庭", "price": 2500, "square": 143.0, "direction": "南 北", "layout": "3室2厅2卫"},
	{"city": "dali", "name": "整租·大理云想山 4室2厅 南", "district": "大理市", "street": "市区", "community": "大理云想山", "price": 3000, "square": 142.0, "direction": "南", "layout": "4室2厅2卫"},
	{"city": "dali", "name": "整租·泰业国际广场 3室2厅 南", "district": "大理市", "street": "市区", "community": "泰业国际广场", "price": 5000, "square": 90.34, "direction": "南", "layout": "3室2厅1卫"},
	{"city": "dali", "name": "整租·洱海天域国际公寓 4室2厅 南/北", "district": "大理市", "street": "市区", "community": "洱海天域国际公寓", "price": 8500, "square": 223.5, "direction": "南 北", "layout": "4室2厅2卫"},
	{"city": "dali", "name": "整租·林勘小区 2室1厅 南/北", "district": "大理市", "street": "市区", "community": "林勘小区", "price": 1000, "square": 50.0, "direction": "南 北", "layout": "2室1厅1卫"},
	{"city": "dali", "name": "整租·大理云想山 3室2厅 东南", "district": "大理市", "street": "市区", "community": "大理云想山", "price": 1900, "square": 109.0, "direction": "东南", "layout": "3室2厅2卫"},
	{"city": "dali", "name": "整租·波罗新村 9室2厅 东/西", "district": "大理市", "street": "市区", "community": "波罗新村", "price": 3500, "square": 295.0, "direction": "东 西", "layout": "9室2厅5卫"},
	{"city": "dali", "name": "整租·沐阳沙河东院 2室2厅 东", "district": "大理市", "street": "市区", "community": "沐阳沙河东院", "price": 1700, "square": 85.0, "direction": "东", "layout": "2室2厅2卫"},
	{"city": "dali", "name": "整租·俊发滨海俊园 2室2厅 东南", "district": "大理市", "street": "市区", "community": "俊发滨海俊园", "price": 2800, "square": 80.0, "direction": "东南", "layout": "2室2厅1卫"},
	{"city": "dali", "name": "整租·鸿泰花园 5室3厅 南/北", "district": "大理市", "street": "市区", "community": "鸿泰花园", "price": 2600, "square": 200.0, "direction": "南 北", "layout": "5室3厅2卫"},
	{"city": "dali", "name": "整租·腾瑞幸福里 1室1厅 西", "district": "大理市", "street": "市区", "community": "腾瑞幸福里", "price": 1200, "square": 98.0, "direction": "西", "layout": "1室1厅0卫"},
	{"city": "dali", "name": "整租·河畔人家 3室2厅 东南", "district": "大理市", "street": "市区", "community": "河畔人家", "price": 2300, "square": 105.48, "direction": "东南", "layout": "3室2厅2卫"},
	{"city": "dali", "name": "整租·河畔金色 3室2厅 南", "district": "大理市", "street": "市区", "community": "河畔金色", "price": 1000, "square": 104.0, "direction": "南", "layout": "3室2厅2卫"},
	{"city": "dali", "name": "整租·天泰大理十畝 3室2厅 西南", "district": "大理市", "street": "市区", "community": "天泰大理十畝", "price": 1800, "square": 112.0, "direction": "西南", "layout": "3室2厅2卫"},
	{"city": "dali", "name": "整租·天泰大理十畝 4室2厅 南", "district": "大理市", "street": "市区", "community": "天泰大理十畝", "price": 2500, "square": 143.0, "direction": "南", "layout": "4室2厅2卫"},
	{"city": "dali", "name": "整租·正阳时代广场 3室2厅 南/北", "district": "大理市", "street": "市区", "community": "正阳时代广场", "price": 1800, "square": 118.0, "direction": "南 北", "layout": "3室2厅2卫"},
	{"city": "dali", "name": "整租·河畔金色 4室2厅 东/南/北", "district": "大理市", "street": "市区", "community": "河畔金色", "price": 3200, "square": 132.0, "direction": "东 南 北", "layout": "4室2厅2卫"},
	{"city": "dali", "name": "整租·建投正阳华府 3室2厅 南/北", "district": "大理市", "street": "市区", "community": "建投正阳华府", "price": 2800, "square": 151.29, "direction": "南 北", "layout": "3室2厅3卫"},
	{"city": "dali", "name": "整租·金星小区 3室2厅 南/北", "district": "大理市", "street": "市区", "community": "金星小区", "price": 2100, "square": 100.0, "direction": "南 北", "layout": "3室2厅1卫"},
	{"city": "dali", "name": "整租·青春海岸公寓 0室1厅 西", "district": "大理市", "street": "市区", "community": "青春海岸公寓", "price": 2500, "square": 93.0, "direction": "西", "layout": "未知室1厅1卫"},
	{"city": "dali", "name": "整租·洱海天域国际公寓 2室2厅 东南", "district": "大理市", "street": "市区", "community": "洱海天域国际公寓", "price": 2300, "square": 86.0, "direction": "东南", "layout": "2室2厅1卫"},
	{"city": "dali", "name": "整租·洱海天域国际公寓 4室2厅 南/北", "district": "大理市", "street": "市区", "community": "洱海天域国际公寓", "price": 8000, "square": 232.0, "direction": "南 北", "layout": "4室2厅2卫"},
	{"city": "dali", "name": "整租·大理公馆 13室3厅 东/西", "district": "大理市", "street": "满江片区", "community": "大理公馆", "price": 30000, "square": 387.86, "direction": "东 西", "layout": "13室3厅3卫"},
	{"city": "dali", "name": "整租·万科·大理·拾叁月 2室2厅 西北", "district": "大理市", "street": "满江片区", "community": "万科·大理·拾叁月", "price": 3500, "square": 86.0, "direction": "西北", "layout": "2室2厅1卫"},
	{"city": "dali", "name": "整租·洱海国际生态城 2室1厅 东", "district": "大理市", "street": "满江片区", "community": "洱海国际生态城", "price": 3000, "square": 125.0, "direction": "东", "layout": "2室1厅1卫"},
	{"city": "dali", "name": "整租·万科·大理·拾叁月 2室2厅 西", "district": "大理市", "street": "满江片区", "community": "万科·大理·拾叁月", "price": 5000, "square": 99.0, "direction": "西", "layout": "2室2厅2卫"},
	{"city": "dali", "name": "整租·怡景尚居 2室1厅 南", "district": "大理市", "street": "满江片区", "community": "怡景尚居", "price": 1600, "square": 89.0, "direction": "南", "layout": "2室1厅1卫"},
	{"city": "dali", "name": "整租·大理公馆 1室0厅 西", "district": "大理市", "street": "满江片区", "community": "大理公馆", "price": 1800, "square": 51.6, "direction": "西", "layout": "1室0厅1卫"},
	{"city": "dali", "name": "整租·万科·大理·拾叁月 2室2厅 西北", "district": "大理市", "street": "满江片区", "community": "万科·大理·拾叁月", "price": 3500, "square": 99.0, "direction": "西北", "layout": "2室2厅2卫"},
	{"city": "dali", "name": "整租·万科·大理·拾叁月 3室2厅 西北", "district": "大理市", "street": "满江片区", "community": "万科·大理·拾叁月", "price": 6000, "square": 154.0, "direction": "西北", "layout": "3室2厅2卫"},
	{"city": "dali", "name": "整租·五洲国际副食品区 2室1厅 南", "district": "大理市", "street": "满江片区", "community": "五洲国际副食品区", "price": 2000, "square": 88.0, "direction": "南", "layout": "2室1厅2卫"},
	{"city": "dali", "name": "整租·大理公馆 1室1厅 南", "district": "大理市", "street": "满江片区", "community": "大理公馆", "price": 2500, "square": 44.0, "direction": "南", "layout": "1室1厅1卫"},
	{"city": "dali", "name": "整租·外滩名著 3室2厅 南", "district": "大理市", "street": "满江片区", "community": "外滩名著", "price": 2600, "square": 125.0, "direction": "南", "layout": "3室2厅2卫"},
	{"city": "dali", "name": "整租·万科·大理·拾叁月 2室1厅 西", "district": "大理市", "street": "满江片区", "community": "万科·大理·拾叁月", "price": 4500, "square": 99.0, "direction": "西", "layout": "2室1厅2卫"},
	{"city": "dali", "name": "整租·银河明珠 4室2厅 南/北", "district": "大理市", "street": "经开区", "community": "银河明珠", "price": 4000, "square": 152.0, "direction": "南 北", "layout": "4室2厅2卫"},
	{"city": "dali", "name": "整租·富海小区 3室2厅 南", "district": "大理市", "street": "经开区", "community": "富海小区", "price": 1500, "square": 99.95, "direction": "南", "layout": "3室2厅1卫"},
	{"city": "dali", "name": "整租·洱海天域 4室2厅 北", "district": "大理市", "street": "经开区", "community": "洱海天域", "price": 17000, "square": 240.0, "direction": "北", "layout": "4室2厅3卫"},
	{"city": "dali", "name": "整租·明珠小区 6室2厅 东", "district": "大理市", "street": "经开区", "community": "明珠小区", "price": 4600, "square": 300.0, "direction": "东", "layout": "6室2厅2卫"},
	{"city": "dali", "name": "整租·洱海龙湾 2室2厅 西", "district": "大理市", "street": "经开区", "community": "洱海龙湾", "price": 3000, "square": 56.0, "direction": "西", "layout": "2室2厅2卫"},
	{"city": "dali", "name": "整租·漫湾花园 3室2厅 东", "district": "大理市", "street": "经开区", "community": "漫湾花园", "price": 2300, "square": 141.0, "direction": "东", "layout": "3室2厅2卫"},
	{"city": "dali", "name": "整租·天景园 3室2厅 西南", "district": "大理市", "street": "经开区", "community": "天景园", "price": 1600, "square": 104.95, "direction": "西南", "layout": "3室2厅1卫"},
	{"city": "dali", "name": "整租·阳光佳苑 2室2厅 南", "district": "大理市", "street": "经开区", "community": "阳光佳苑", "price": 1000, "square": 58.0, "direction": "南", "layout": "2室2厅1卫"},
	{"city": "dali", "name": "整租·路政支队 3室2厅 南/北", "district": "大理市", "street": "经开区", "community": "路政支队", "price": 2500, "square": 123.0, "direction": "南 北", "layout": "3室2厅2卫"},
	{"city": "dali", "name": "整租·漾江林业局宿舍 2室1厅 东南", "district": "大理市", "street": "经开区", "community": "漾江林业局宿舍", "price": 1100, "square": 80.0, "direction": "东南", "layout": "2室1厅1卫"},
	{"city": "dali", "name": "整租·漾濞路51号 7室4厅 东/西", "district": "大理市", "street": "经开区", "community": "漾濞路51号", "price": 10000, "square": 460.0, "direction": "东 西", "layout": "7室4厅6卫"},
	{"city": "dali", "name": "整租·民航小区 3室2厅 南/北", "district": "大理市", "street": "经开区", "community": "民航小区", "price": 1300, "square": 90.0, "direction": "南 北", "layout": "3室2厅1卫"},
	{"city": "dali", "name": "整租·达人联盟 4室2厅 南", "district": "大理市", "street": "经开区", "community": "达人联盟", "price": 2800, "square": 130.0, "direction": "南", "layout": "4室2厅2卫"},
	{"city": "dali", "name": "整租·大理阳光 3室2厅 西南/东北", "district": "大理市", "street": "海东", "community": "大理阳光", "price": 2500, "square": 158.0, "direction": "西南 东北", "layout": "3室2厅2卫"},
	{"city": "dali", "name": "整租·纳思海岸春天 1室0厅 东", "district": "大理市", "street": "海东", "community": "纳思海岸春天", "price": 850, "square": 43.9, "direction": "东", "layout": "1室0厅1卫"},
	{"city": "dali", "name": "整租·东岸泽园 4室2厅 东南", "district": "大理市", "street": "海东", "community": "东岸泽园", "price": 3000, "square": 197.0, "direction": "东南", "layout": "4室2厅3卫"},
	{"city": "dali", "name": "整租·梦云南海东方 6室3厅 东/西", "district": "大理市", "street": "海东", "community": "梦云南海东方", "price": 18000, "square": 189.0, "direction": "东 西", "layout": "6室3厅6卫"},
	{"city": "dali", "name": "整租·东岸桂园小区 4室2厅 南", "district": "大理市", "street": "海东", "community": "东岸桂园小区", "price": 3000, "square": 132.0, "direction": "南", "layout": "4室2厅2卫"},
	{"city": "dali", "name": "整租·东岸和园 4室2厅 南/北", "district": "大理市", "street": "海东", "community": "东岸和园", "price": 2800, "square": 200.7, "direction": "南 北", "layout": "4室2厅3卫"},
	{"city": "dali", "name": "整租·东岸清园 1室1厅 南", "district": "大理市", "street": "海东", "community": "东岸清园", "price": 900, "square": 54.0, "direction": "南", "layout": "1室1厅1卫"},
	{"city": "dali", "name": "整租·东岸馨园 3室2厅 南/北", "district": "大理市", "street": "海东", "community": "东岸馨园", "price": 2500, "square": 134.0, "direction": "南 北", "layout": "3室2厅2卫"},
	{"city": "dali", "name": "整租·东岸泽园 3室2厅 南/北", "district": "大理市", "street": "海东", "community": "东岸泽园", "price": 2500, "square": 134.0, "direction": "南 北", "layout": "3室2厅2卫"},
	{"city": "dali", "name": "整租·东岸泽园 3室2厅 南/北", "district": "大理市", "street": "海东", "community": "东岸泽园", "price": 3000, "square": 134.0, "direction": "南 北", "layout": "3室2厅3卫"},
	{"city": "dali", "name": "整租·东岸沁园 3室1厅 南/北", "district": "大理市", "street": "海东", "community": "东岸沁园", "price": 1800, "square": 90.0, "direction": "南 北", "layout": "3室1厅1卫"},
	{"city": "dali", "name": "整租·东岸清园 3室2厅 西南", "district": "大理市", "street": "海东", "community": "东岸清园", "price": 2500, "square": 134.0, "direction": "西南", "layout": "3室2厅2卫"},
	{"city": "dali", "name": "整租·梦云南海东方 6室2厅 西南", "district": "大理市", "street": "海东", "community": "梦云南海东方", "price": 25000, "square": 300.0, "direction": "西南", "layout": "6室2厅6卫"},
	{"city": "dali", "name": "整租·纳思海岸春天 1室0厅 东", "district": "大理市", "street": "海东", "community": "纳思海岸春天", "price": 850, "square": 43.9, "direction": "东", "layout": "1室0厅1卫"},
	{"city": "dali", "name": "整租·东岸泽园 4室2厅 东南", "district": "大理市", "street": "海东", "community": "东岸泽园", "price": 3000, "square": 197.0, "direction": "东南", "layout": "4室2厅3卫"},
	{"city": "dali", "name": "整租·梦云南海东方 6室3厅 东/西", "district": "大理市", "street": "海东", "community": "梦云南海东方", "price": 18000, "square": 189.0, "direction": "东 西", "layout": "6室3厅6卫"},
	{"city": "dali", "name": "整租·东岸桂园小区 4室2厅 南", "district": "大理市", "street": "海东", "community": "东岸桂园小区", "price": 3000, "square": 132.0, "direction": "南", "layout": "4室2厅2卫"},
	{"city": "dali", "name": "整租·东岸和园 4室2厅 南/北", "district": "大理市", "street": "海东", "community": "东岸和园", "price": 2800, "square": 200.7, "direction": "南 北", "layout": "4室2厅3卫"},
	{"city": "dali", "name": "整租·东岸清园 1室1厅 南", "district": "大理市", "street": "海东", "community": "东岸清园", "price": 900, "square": 54.0, "direction": "南", "layout": "1室1厅1卫"},
	{"city": "dali", "name": "整租·东岸馨园 3室2厅 南/北", "district": "大理市", "street": "海东", "community": "东岸馨园", "price": 2500, "square": 134.0, "direction": "南 北", "layout": "3室2厅2卫"},
	{"city": "dali", "name": "整租·东岸泽园 3室2厅 南/北", "district": "大理市", "street": "海东", "community": "东岸泽园", "price": 2500, "square": 134.0, "direction": "南 北", "layout": "3室2厅2卫"},
	{"city": "dali", "name": "整租·东岸泽园 3室2厅 南/北", "district": "大理市", "street": "海东", "community": "东岸泽园", "price": 3000, "square": 134.0, "direction": "南 北", "layout": "3室2厅3卫"},
	{"city": "dali", "name": "整租·东岸沁园 3室1厅 南/北", "district": "大理市", "street": "海东", "community": "东岸沁园", "price": 1800, "square": 90.0, "direction": "南 北", "layout": "3室1厅1卫"},
	{"city": "dali", "name": "整租·东岸清园 3室2厅 西南", "district": "大理市", "street": "海东", "community": "东岸清园", "price": 2500, "square": 134.0, "direction": "西南", "layout": "3室2厅2卫"},
	{"city": "dali", "name": "整租·梦云南海东方 4室2厅 南", "district": "大理市", "street": "海东", "community": "梦云南海东方", "price": 8000, "square": 212.0, "direction": "南", "layout": "4室2厅3卫"},
	{"city": "dali", "name": "整租·梦云南海东方 4室2厅 西南", "district": "大理市", "street": "海东", "community": "梦云南海东方", "price": 12000, "square": 198.0, "direction": "西南", "layout": "4室2厅3卫"},
	{"city": "dali", "name": "整租·钜融城左岸高地 4室2厅 复式 东/西", "district": "大理市", "street": "古城", "community": "钜融城左岸高地", "price": 5500, "square": 162.0, "direction": "东 西", "layout": "4室2厅2卫"},
	{"city": "dali", "name": "整租·钜融城左岸高地 5室2厅 东/西", "district": "大理市", "street": "古城", "community": "钜融城左岸高地", "price": 5500, "square": 217.0, "direction": "东 西", "layout": "5室2厅4卫"},
	{"city": "dali", "name": "整租·钜融城左岸高地 3室3厅 南/北", "district": "大理市", "street": "古城", "community": "钜融城左岸高地", "price": 3800, "square": 330.0, "direction": "南 北", "layout": "3室3厅5卫"},
	{"city": "dali", "name": "整租·大理朴墅 3室2厅 东/西", "district": "大理市", "street": "古城", "community": "大理朴墅", "price": 8000, "square": 137.0, "direction": "东 西", "layout": "3室2厅4卫"},
	{"city": "dali", "name": "整租·大理的小院子南区 4室2厅 东", "district": "大理市", "street": "古城", "community": "大理的小院子南区", "price": 5000, "square": 220.0, "direction": "东", "layout": "4室2厅3卫"},
	{"city": "dali", "name": "整租·大理国际艺术家园区 4室2厅 东/西/北", "district": "大理市", "street": "古城", "community": "大理国际艺术家园区", "price": 10000, "square": 257.0, "direction": "东 西 北", "layout": "4室2厅2卫"},
	{"city": "dali", "name": "整租·善德居随云 4室2厅 东/西", "district": "大理市", "street": "古城", "community": "善德居随云", "price": 6000, "square": 255.0, "direction": "东 西", "layout": "4室2厅3卫"},
	{"city": "dali", "name": "整租·大理市大理古城建行宿舍 2室1厅 南/北", "district": "大理市", "street": "古城", "community": "大理市大理古城建行宿舍", "price": 3600, "square": 63.0, "direction": "南 北", "layout": "2室1厅1卫"},
	{"city": "dali", "name": "整租·玉洱路93号 4室2厅 南/北", "district": "大理市", "street": "古城", "community": "玉洱路93号", "price": 11000, "square": 160.0, "direction": "南 北", "layout": "4室2厅1卫"},
	{"city": "dali", "name": "整租·感通别墅 3室0厅 东/西", "district": "大理市", "street": "古城", "community": "感通别墅", "price": 3400, "square": 80.0, "direction": "东 西", "layout": "3室0厅2卫"},
	{"city": "dali", "name": "整租·感通别墅 1室1厅 东/西", "district": "大理市", "street": "古城", "community": "感通别墅", "price": 1700, "square": 37.0, "direction": "东 西", "layout": "1室1厅1卫"},
	{"city": "dali", "name": "整租·大理的小院子北区 2室1厅 东/西", "district": "大理市", "street": "古城", "community": "大理的小院子北区", "price": 7000, "square": 100.0, "direction": "东 西", "layout": "2室1厅1卫"},
	{"city": "dali", "name": "整租·1806搬迁小镇 9室2厅 南/北", "district": "大理市", "street": "古城", "community": "1806搬迁小镇", "price": 6500, "square": 428.0, "direction": "南 北", "layout": "9室2厅7卫"},
	{"city": "dali", "name": "整租·大理的小院子中区 3室1厅 东/西", "district": "大理市", "street": "古城", "community": "大理的小院子中区", "price": 6500, "square": 119.27, "direction": "东 西", "layout": "3室1厅3卫"},
	{"city": "dali", "name": "整租·钜融城左岸高地 4室2厅 复式 东/西", "district": "大理市", "street": "古城", "community": "钜融城左岸高地", "price": 5500, "square": 162.0, "direction": "东 西", "layout": "4室2厅2卫"},
	{"city": "dali", "name": "整租·钜融城左岸高地 5室2厅 东/西", "district": "大理市", "street": "古城", "community": "钜融城左岸高地", "price": 5500, "square": 217.0, "direction": "东 西", "layout": "5室2厅4卫"},
	{"city": "dali", "name": "整租·钜融城左岸高地 3室3厅 南/北", "district": "大理市", "street": "古城", "community": "钜融城左岸高地", "price": 3800, "square": 330.0, "direction": "南 北", "layout": "3室3厅5卫"},
	{"city": "dali", "name": "整租·大理朴墅 3室2厅 东/西", "district": "大理市", "street": "古城", "community": "大理朴墅", "price": 8000, "square": 137.0, "direction": "东 西", "layout": "3室2厅4卫"},
	{"city": "dali", "name": "整租·大理的小院子南区 4室2厅 东", "district": "大理市", "street": "古城", "community": "大理的小院子南区", "price": 5000, "square": 220.0, "direction": "东", "layout": "4室2厅3卫"},
	{"city": "dali", "name": "整租·大理国际艺术家园区 4室2厅 东/西/北", "district": "大理市", "street": "古城", "community": "大理国际艺术家园区", "price": 10000, "square": 257.0, "direction": "东 西 北", "layout": "4室2厅2卫"},
	{"city": "dali", "name": "整租·善德居随云 4室2厅 东/西", "district": "大理市", "street": "古城", "community": "善德居随云", "price": 6000, "square": 255.0, "direction": "东 西", "layout": "4室2厅3卫"},
	{"city": "dali", "name": "整租·大理市大理古城建行宿舍 2室1厅 南/北", "district": "大理市", "street": "古城", "community": "大理市大理古城建行宿舍", "price": 3600, "square": 63.0, "direction": "南 北", "layout": "2室1厅1卫"},
	{"city": "dali", "name": "整租·玉洱路93号 4室2厅 南/北", "district": "大理市", "street": "古城", "community": "玉洱路93号", "price": 11000, "square": 160.0, "direction": "南 北", "layout": "4室2厅1卫"},
	{"city": "dali", "name": "整租·感通别墅 3室0厅 东/西", "district": "大理市", "street": "古城", "community": "感通别墅", "price": 3400, "square": 80.0, "direction": "东 西", "layout": "3室0厅2卫"},
	{"city": "dali", "name": "整租·感通别墅 1室1厅 东/西", "district": "大理市", "street": "古城", "community": "感通别墅", "price": 1700, "square": 37.0, "direction": "东 西", "layout": "1室1厅1卫"},
	{"city": "dali", "name": "整租·大理的小院子北区 2室1厅 东/西", "district": "大理市", "street": "古城", "community": "大理的小院子北区", "price": 7000, "square": 100.0, "direction": "东 西", "layout": "2室1厅1卫"},
	{"city": "dali", "name": "整租·凤仪庄园 3室2厅 南/北", "district": "大理市", "street": "凤仪", "community": "凤仪庄园", "price": 2000, "square": 120.0, "direction": "南 北", "layout": "3室2厅2卫"},
	{"city": "dali", "name": "整租·凤庭苑 3室2厅 东", "district": "大理市", "street": "凤仪", "community": "凤庭苑", "price": 1500, "square": 95.0, "direction": "东", "layout": "3室2厅1卫"},
	{"city": "dali", "name": "整租·大理慢谷-世界健康小镇 1室1厅 南", "district": "大理市", "street": "凤仪", "community": "大理慢谷-世界健康小镇", "price": 1800, "square": 53.0, "direction": "南", "layout": "1室1厅1卫"},
	{"city": "dali", "name": "整租·大理慢谷-世界健康小镇 2室2厅 西南", "district": "大理市", "street": "凤仪", "community": "大理慢谷-世界健康小镇", "price": 1500, "square": 90.0, "direction": "西南", "layout": "2室2厅1卫"},
	{"city": "dali", "name": "整租·凤仪庄园 3室2厅 南/北", "district": "大理市", "street": "凤仪", "community": "凤仪庄园", "price": 1500, "square": 96.0, "direction": "南 北", "layout": "3室2厅1卫"},
	{"city": "dali", "name": "整租·大理慢谷-世界健康小镇 3室1厅 东南", "district": "大理市", "street": "凤仪", "community": "大理慢谷-世界健康小镇", "price": 1700, "square": 87.0, "direction": "东南", "layout": "3室1厅1卫"},
	{"city": "dali", "name": "整租·凤仪供电所宿舍 3室2厅 东/西", "district": "大理市", "street": "凤仪", "community": "凤仪供电所宿舍", "price": 1400, "square": 99.94, "direction": "东 西", "layout": "3室2厅1卫"},
	{"city": "dali", "name": "整租·大理慢谷-世界健康小镇 3室2厅 南/北", "district": "大理市", "street": "凤仪", "community": "大理慢谷-世界健康小镇", "price": 2500, "square": 84.0, "direction": "南 北", "layout": "3室2厅1卫"},
	{"city": "dali", "name": "整租·凤庭苑 3室2厅 东", "district": "大理市", "street": "凤仪", "community": "凤庭苑", "price": 1500, "square": 80.0, "direction": "东", "layout": "3室2厅1卫"},
	{"city": "dali", "name": "整租·大理慢谷-世界健康小镇 2室2厅 南", "district": "大理市", "street": "凤仪", "community": "大理慢谷-世界健康小镇", "price": 2300, "square": 91.5, "direction": "南", "layout": "2室2厅1卫"},
	{"city": "dali", "name": "整租·凤仪庄园 3室2厅 南/北", "district": "大理市", "street": "凤仪", "community": "凤仪庄园", "price": 1600, "square": 96.8, "direction": "南 北", "layout": "3室2厅1卫"},
	{"city": "dali", "name": "整租·大理慢谷-世界健康小镇 1室0厅 南", "district": "大理市", "street": "凤仪", "community": "大理慢谷-世界健康小镇", "price": 1200, "square": 51.5, "direction": "南", "layout": "1室0厅1卫"},
	{"city": "dali", "name": "整租·大理慢谷-世界健康小镇 3室1厅 南", "district": "大理市", "street": "凤仪", "community": "大理慢谷-世界健康小镇", "price": 1200, "square": 84.13, "direction": "南", "layout": "3室1厅1卫"},
	{"city": "dali", "name": "整租·大理慢谷-世界健康小镇 1室0厅 南", "district": "大理市", "street": "凤仪", "community": "大理慢谷-世界健康小镇", "price": 1200, "square": 51.5, "direction": "南", "layout": "1室0厅1卫"},
	{"city": "dali", "name": "整租·大理慢谷-世界健康小镇 3室1厅 南", "district": "大理市", "street": "凤仪", "community": "大理慢谷-世界健康小镇", "price": 1200, "square": 84.13, "direction": "南", "layout": "3室1厅1卫"},
	{"city": "dali", "name": "整租·大理慢谷-世界健康小镇 1室1厅 南", "district": "大理市", "street": "凤仪", "community": "大理慢谷-世界健康小镇", "price": 900, "square": 53.0, "direction": "南", "layout": "1室1厅1卫"},
	{"city": "dali", "name": "整租·大理慢谷-世界健康小镇 3室2厅 南/北", "district": "大理市", "street": "凤仪", "community": "大理慢谷-世界健康小镇", "price": 2500, "square": 87.0, "direction": "南 北", "layout": "3室2厅1卫"},
	{"city": "dali", "name": "整租·大理慢谷-世界健康小镇 3室2厅 南", "district": "大理市", "street": "凤仪", "community": "大理慢谷-世界健康小镇", "price": 2400, "square": 82.0, "direction": "南", "layout": "3室2厅2卫"},
	{"city": "dali", "name": "整租·凤仪庄园 2室2厅 南/北", "district": "大理市", "street": "凤仪", "community": "凤仪庄园", "price": 1450, "square": 77.0, "direction": "南 北", "layout": "2室2厅1卫"},
	{"city": "dali", "name": "整租·大理慢谷-世界健康小镇 2室2厅 东", "district": "大理市", "street": "凤仪", "community": "大理慢谷-世界健康小镇", "price": 1800, "square": 89.0, "direction": "东", "layout": "2室2厅1卫"},
	{"city": "dali", "name": "整租·凤庭苑 3室2厅 东/西", "district": "大理市", "street": "凤仪", "community": "凤庭苑", "price": 1300, "square": 104.85, "direction": "东 西", "layout": "3室2厅1卫"},
	{"city": "dali", "name": "整租·凤仪庄园 3室2厅 南/北", "district": "大理市", "street": "凤仪", "community": "凤仪庄园", "price": 1500, "square": 96.0, "direction": "南 北", "layout": "3室2厅1卫"},
	{"city": "dali", "name": "整租·大理慢谷-世界健康小镇 2室2厅 南/北", "district": "大理市", "street": "凤仪", "community": "大理慢谷-世界健康小镇", "price": 1800, "square": 95.39, "direction": "南 北", "layout": "2室2厅2卫"},
	{"city": "dali", "name": "整租·凤仪庄园 3室2厅 南/北", "district": "大理市", "street": "凤仪", "community": "凤仪庄园", "price": 1600, "square": 108.0, "direction": "南 北", "layout": "3室2厅2卫"},
	{"city": "dali", "name": "整租·凤仪庄园 3室2厅 南/北", "district": "大理市", "street": "凤仪", "community": "凤仪庄园", "price": 2000, "square": 120.0, "direction": "南 北", "layout": "3室2厅2卫"},
	{"city": "dali", "name": "整租·凤仪庄园 3室2厅 南/北", "district": "大理市", "street": "凤仪", "community": "凤仪庄园", "price": 1400, "square": 96.0, "direction": "南 北", "layout": "3室2厅1卫"},
	{"city": "dali", "name": "整租·邑水花都 4室2厅 南", "district": "大理市", "street": "下关北区", "community": "邑水花都", "price": 20000, "square": 380.0, "direction": "南", "layout": "4室2厅5卫"},
	{"city": "dali", "name": "整租·滨河苑 2室2厅 东/西", "district": "大理市", "street": "下关北区", "community": "滨河苑", "price": 1000, "square": 63.0, "direction": "东 西", "layout": "2室2厅1卫"},
	{"city": "dali", "name": "整租·美登小区 3室2厅 东/西", "district": "大理市", "street": "下关北区", "community": "美登小区", "price": 1500, "square": 90.5, "direction": "东 西", "layout": "3室2厅1卫"},
	{"city": "dali", "name": "整租·洱海庄园 1室0厅 南", "district": "大理市", "street": "下关北区", "community": "洱海庄园", "price": 1300, "square": 56.0, "direction": "南", "layout": "1室0厅1卫"},
	{"city": "dali", "name": "整租·山水清城小区 3室2厅 东/西", "district": "大理市", "street": "下关北区", "community": "山水清城小区", "price": 2500, "square": 130.26, "direction": "东 西", "layout": "3室2厅2卫"},
	{"city": "dali", "name": "整租·艺墅花乡 2室1厅 跃层 南", "district": "大理市", "street": "下关北区", "community": "艺墅花乡", "price": 2800, "square": 67.0, "direction": "南", "layout": "2室1厅1卫"},
	{"city": "dali", "name": "整租·华辰玉海豪庭 3室2厅 西", "district": "大理市", "street": "下关北区", "community": "华辰玉海豪庭", "price": 2800, "square": 92.0, "direction": "西", "layout": "3室2厅1卫"},
	{"city": "dali", "name": "整租·龙悦华府 3室2厅 南", "district": "大理市", "street": "下关北区", "community": "龙悦华府", "price": 4500, "square": 123.0, "direction": "南", "layout": "3室2厅2卫"},
	{"city": "dali", "name": "整租·大理州社会保险局职工住宅区 4室2厅 南/北", "district": "大理市", "street": "下关北区", "community": "大理州社会保险局职工住宅区", "price": 2300, "square": 143.0, "direction": "南 北", "layout": "4室2厅2卫"},
	{"city": "dali", "name": "整租·太和苑 3室2厅 南", "district": "大理市", "street": "下关北区", "community": "太和苑", "price": 1500, "square": 83.35, "direction": "南", "layout": "3室2厅1卫"},
	{"city": "dali", "name": "整租·北苑商住区 3室1厅 东/西", "district": "大理市", "street": "下关北区", "community": "北苑商住区", "price": 2000, "square": 87.0, "direction": "东 西", "layout": "3室1厅1卫"},
	{"city": "dali", "name": "整租·艺墅花乡 4室1厅 南/北", "district": "大理市", "street": "下关北区", "community": "艺墅花乡", "price": 4800, "square": 207.19, "direction": "南 北", "layout": "4室1厅1卫"},
	{"city": "dali", "name": "整租·花韵蓝湾 3室2厅 南", "district": "大理市", "street": "下关北区", "community": "花韵蓝湾", "price": 2200, "square": 96.5, "direction": "南", "layout": "3室2厅2卫"},
	{"city": "dali", "name": "整租·龙悦华府 3室2厅 南/北", "district": "大理市", "street": "下关北区", "community": "龙悦华府", "price": 4200, "square": 117.0, "direction": "南 北", "layout": "3室2厅2卫"},
	{"city": "dali", "name": "整租·昇耀新里程 2室2厅 东南", "district": "大理市", "street": "下关北区", "community": "昇耀新里程", "price": 1400, "square": 92.0, "direction": "东南", "layout": "2室2厅1卫"},
	{"city": "dali", "name": "整租·建元公寓 3室2厅 南", "district": "大理市", "street": "下关北区", "community": "建元公寓", "price": 1200, "square": 67.19, "direction": "南", "layout": "3室2厅1卫"},
	{"city": "dali", "name": "整租·华辰玉海豪庭 3室2厅 南/北", "district": "大理市", "street": "下关北区", "community": "华辰玉海豪庭", "price": 2700, "square": 91.0, "direction": "南 北", "layout": "3室2厅1卫"},
	{"city": "dali", "name": "整租·惠丰瑞城 3室2厅 东南", "district": "大理市", "street": "下关北区", "community": "惠丰瑞城", "price": 2800, "square": 144.0, "direction": "东南", "layout": "3室2厅2卫"},
	{"city": "dali", "name": "整租·惠丰瑞城 2室2厅 东南", "district": "大理市", "street": "下关北区", "community": "惠丰瑞城", "price": 2000, "square": 86.0, "direction": "东南", "layout": "2室2厅1卫"},
	{"city": "dali", "name": "整租·惠丰瑞城 3室2厅 南", "district": "大理市", "street": "下关北区", "community": "惠丰瑞城", "price": 2000, "square": 95.0, "direction": "南", "layout": "3室2厅1卫"},
	{"city": "dali", "name": "整租·龙悦华府 3室2厅 南/北", "district": "大理市", "street": "下关北区", "community": "龙悦华府", "price": 4000, "square": 142.0, "direction": "南 北", "layout": "3室2厅2卫"},
	{"city": "dali", "name": "整租·洱海庄园 3室2厅 南", "district": "大理市", "street": "下关北区", "community": "洱海庄园", "price": 3000, "square": 127.31, "direction": "南", "layout": "3室2厅2卫"},
	{"city": "dali", "name": "整租·兴国路商品房 2室1厅 南/北", "district": "大理市", "street": "下关北区", "community": "兴国路商品房", "price": 1200, "square": 58.0, "direction": "南 北", "layout": "2室1厅1卫"},
	{"city": "dali", "name": "整租·俊发滨海俊园 3室2厅 东南", "district": "大理市", "street": "市区", "community": "俊发滨海俊园", "price": 3000, "square": 93.0, "direction": "东南", "layout": "3室2厅1卫"},
	{"city": "dali", "name": "整租·下关镇宁和社区 2室1厅 南", "district": "大理市", "street": "市区", "community": "下关镇宁和社区", "price": 800, "square": 67.14, "direction": "南", "layout": "2室1厅1卫"},
	{"city": "dali", "name": "整租·大理州医药有限责任公司职工宿舍楼 3室2厅 东/西", "district": "大理市", "street": "市区", "community": "大理州医药有限责任公司职工宿舍楼", "price": 2100, "square": 88.07, "direction": "东 西", "layout": "3室2厅1卫"},
	{"city": "dali", "name": "整租·俊发滨海俊园 4室2厅 北", "district": "大理市", "street": "市区", "community": "俊发滨海俊园", "price": 4500, "square": 177.0, "direction": "北", "layout": "4室2厅2卫"},
	{"city": "dali", "name": "整租·青春海岸公寓 2室2厅 跃层 东/西", "district": "大理市", "street": "市区", "community": "青春海岸公寓", "price": 1500, "square": 84.42, "direction": "东 西", "layout": "2室2厅1卫"},
	{"city": "dali", "name": "整租·大理华兴公司吉兴苑小区 3室2厅 东/西", "district": "大理市", "street": "市区", "community": "大理华兴公司吉兴苑小区", "price": 1600, "square": 107.0, "direction": "东 西", "layout": "3室2厅1卫"},
	{"city": "dali", "name": "整租·大理云想山 3室2厅 南", "district": "大理市", "street": "市区", "community": "大理云想山", "price": 2500, "square": 109.0, "direction": "南", "layout": "3室2厅2卫"},
	{"city": "dali", "name": "整租·河畔金色 3室2厅 西/北", "district": "大理市", "street": "市区", "community": "河畔金色", "price": 2000, "square": 104.0, "direction": "西 北", "layout": "3室2厅2卫"},
	{"city": "dali", "name": "整租·河畔金色 3室2厅 北", "district": "大理市", "street": "市区", "community": "河畔金色", "price": 2500, "square": 104.0, "direction": "北", "layout": "3室2厅1卫"},
	{"city": "dali", "name": "整租·金星小区 3室1厅 东", "district": "大理市", "street": "市区", "community": "金星小区", "price": 1100, "square": 72.0, "direction": "东", "layout": "3室1厅1卫"},
	{"city": "dali", "name": "整租·泰安新城 3室2厅 东/南", "district": "大理市", "street": "市区", "community": "泰安新城", "price": 2800, "square": 124.0, "direction": "东 南", "layout": "3室2厅2卫"},
	{"city": "dali", "name": "整租·河畔金色 4室2厅 东北", "district": "大理市", "street": "市区", "community": "河畔金色", "price": 2800, "square": 133.0, "direction": "东北", "layout": "4室2厅2卫"},
	{"city": "dali", "name": "整租·建投正阳华府 3室2厅 东/南", "district": "大理市", "street": "市区", "community": "建投正阳华府", "price": 1500, "square": 126.65, "direction": "东 南", "layout": "3室2厅2卫"},
	{"city": "dali", "name": "整租·泰玺·茗苑 4室2厅 南/北", "district": "大理市", "street": "市区", "community": "泰玺·茗苑", "price": 2700, "square": 134.0, "direction": "南 北", "layout": "4室2厅2卫"},
	{"city": "dali", "name": "整租·河畔人家 1室1厅 西北", "district": "大理市", "street": "市区", "community": "河畔人家", "price": 1400, "square": 61.3, "direction": "西北", "layout": "1室1厅1卫"},
	{"city": "dali", "name": "整租·森工局宿舍 5室3厅 复式 南/北", "district": "大理市", "street": "市区", "community": "森工局宿舍", "price": 3000, "square": 271.0, "direction": "南 北", "layout": "5室3厅4卫"},
	{"city": "dali", "name": "整租·锦达豪庭 4室2厅 南/北", "district": "大理市", "street": "市区", "community": "锦达豪庭", "price": 3000, "square": 173.16, "direction": "南 北", "layout": "4室2厅2卫"},
	{"city": "dali", "name": "整租·俊发滨海俊园 2室1厅 西南", "district": "大理市", "street": "市区", "community": "俊发滨海俊园", "price": 1500, "square": 51.0, "direction": "西南", "layout": "2室1厅1卫"},
	{"city": "dali", "name": "整租·河畔金色 4室2厅 东/北", "district": "大理市", "street": "市区", "community": "河畔金色", "price": 1800, "square": 132.0, "direction": "东 北", "layout": "4室2厅2卫"},
	{"city": "dali", "name": "整租·俊发滨海俊园 5室2厅 东南", "district": "大理市", "street": "市区", "community": "俊发滨海俊园", "price": 25000, "square": 365.0, "direction": "东南", "layout": "5室2厅5卫"},
	{"city": "dali", "name": "整租·泰安新城 3室2厅 南", "district": "大理市", "street": "市区", "community": "泰安新城", "price": 1800, "square": 91.0, "direction": "南", "layout": "3室2厅1卫"},
	{"city": "dali", "name": "整租·大理滇西商务中心 2室2厅 东/西", "district": "大理市", "street": "市区", "community": "大理滇西商务中心", "price": 1700, "square": 95.33, "direction": "东 西", "layout": "2室2厅1卫"},
	{"city": "dali", "name": "整租·大理云想山 4室2厅 东南", "district": "大理市", "street": "市区", "community": "大理云想山", "price": 5800, "square": 146.0, "direction": "东南", "layout": "4室2厅2卫"},
	{"city": "dali", "name": "整租·万科·大理·拾叁月 3室2厅 西", "district": "大理市", "street": "满江片区", "community": "万科·大理·拾叁月", "price": 5000, "square": 130.0, "direction": "西", "layout": "3室2厅2卫"},
	{"city": "dali", "name": "整租·怡景尚居 2室2厅 东南", "district": "大理市", "street": "满江片区", "community": "怡景尚居", "price": 2500, "square": 89.0, "direction": "东南", "layout": "2室2厅1卫"},
	{"city": "dali", "name": "整租·大理华城海琴湾小区 4室2厅 东", "district": "大理市", "street": "满江片区", "community": "大理华城海琴湾小区", "price": 3200, "square": 144.65, "direction": "东", "layout": "4室2厅2卫"},
	{"city": "dali", "name": "整租·东盟国际 2室2厅 西", "district": "大理市", "street": "满江片区", "community": "东盟国际", "price": 1000, "square": 79.82, "direction": "西", "layout": "2室2厅1卫"},
	{"city": "dali", "name": "整租·外滩名著 3室2厅 东南", "district": "大理市", "street": "满江片区", "community": "外滩名著", "price": 2600, "square": 119.64, "direction": "东南", "layout": "3室2厅2卫"},
	{"city": "dali", "name": "整租·金K海景 3室2厅 西", "district": "大理市", "street": "满江片区", "community": "金K海景", "price": 2500, "square": 87.0, "direction": "西", "layout": "3室2厅1卫"},
	{"city": "dali", "name": "整租·大华·锦绣华城 3室2厅 南/西/北", "district": "大理市", "street": "满江片区", "community": "大华·锦绣华城", "price": 2100, "square": 114.0, "direction": "南 西 北", "layout": "3室2厅2卫"},
	{"city": "dali", "name": "整租·金K海景 1室1厅 东/东南/南", "district": "大理市", "street": "满江片区", "community": "金K海景", "price": 1500, "square": 43.61, "direction": "东 东南 南", "layout": "1室1厅1卫"},
	{"city": "dali", "name": "整租·万科·大理·拾叁月 3室2厅 东南", "district": "大理市", "street": "满江片区", "community": "万科·大理·拾叁月", "price": 2800, "square": 108.0, "direction": "东南", "layout": "3室2厅2卫"},
	{"city": "dali", "name": "整租·大理公馆 3室2厅 南", "district": "大理市", "street": "满江片区", "community": "大理公馆", "price": 2800, "square": 110.0, "direction": "南", "layout": "3室2厅3卫"},
	{"city": "dali", "name": "整租·万科·大理·拾叁月 2室1厅 西", "district": "大理市", "street": "满江片区", "community": "万科·大理·拾叁月", "price": 4000, "square": 99.0, "direction": "西", "layout": "2室1厅2卫"},
	{"city": "dali", "name": "整租·泛亚国际 4室2厅 南", "district": "大理市", "street": "经开区", "community": "泛亚国际", "price": 2200, "square": 137.5, "direction": "南", "layout": "4室2厅2卫"},
	{"city": "dali", "name": "整租·第3时空 1室0厅 南", "district": "大理市", "street": "经开区", "community": "第3时空", "price": 1100, "square": 48.0, "direction": "南", "layout": "1室0厅1卫"},
	{"city": "dali", "name": "整租·观天下 3室2厅 东南", "district": "大理市", "street": "经开区", "community": "观天下", "price": 2200, "square": 114.0, "direction": "东南", "layout": "3室2厅2卫"},
	{"city": "dali", "name": "整租·漾濞路269号 3室2厅 东/西", "district": "大理市", "street": "经开区", "community": "漾濞路269号", "price": 1500, "square": 110.0, "direction": "东 西", "layout": "3室2厅1卫"},
	{"city": "dali", "name": "整租·达人联盟 2室2厅 北", "district": "大理市", "street": "经开区", "community": "达人联盟", "price": 1300, "square": 85.0, "direction": "北", "layout": "2室2厅1卫"},
	{"city": "dali", "name": "整租·州二院生活区 3室2厅 南/北", "district": "大理市", "street": "经开区", "community": "州二院生活区", "price": 1300, "square": 100.0, "direction": "南 北", "layout": "3室2厅1卫"},
	{"city": "dali", "name": "整租·下关路桥一公司宿舍 3室1厅 南", "district": "大理市", "street": "经开区", "community": "下关路桥一公司宿舍", "price": 1500, "square": 104.0, "direction": "南", "layout": "3室1厅1卫"},
	{"city": "dali", "name": "整租·文献村 1室1厅 东", "district": "大理市", "street": "经开区", "community": "文献村", "price": 1400, "square": 68.0, "direction": "东", "layout": "1室1厅1卫"},
	{"city": "dali", "name": "整租·富海小区 3室2厅 南", "district": "大理市", "street": "经开区", "community": "富海小区", "price": 1300, "square": 102.0, "direction": "南", "layout": "3室2厅1卫"},
	{"city": "dali", "name": "整租·佳诚福苑 2室2厅 东", "district": "大理市", "street": "经开区", "community": "佳诚福苑", "price": 1300, "square": 91.0, "direction": "东", "layout": "2室2厅1卫"},
	{"city": "dali", "name": "整租·文献村 2室2厅 东", "district": "大理市", "street": "经开区", "community": "文献村", "price": 3000, "square": 150.0, "direction": "东", "layout": "2室2厅2卫"},
	{"city": "dali", "name": "整租·梦云南海东方 5室3厅 东/南/西", "district": "大理市", "street": "海东", "community": "梦云南海东方", "price": 25000, "square": 300.0, "direction": "东 南 西", "layout": "5室3厅4卫"},
	{"city": "dali", "name": "整租·梦云南海东方 7室2厅 西", "district": "大理市", "street": "海东", "community": "梦云南海东方", "price": 30000, "square": 900.0, "direction": "西", "layout": "7室2厅7卫"},
	{"city": "dali", "name": "整租·梦云南海东方 5室2厅 东南", "district": "大理市", "street": "海东", "community": "梦云南海东方", "price": 16666, "square": 282.56, "direction": "东南", "layout": "5室2厅4卫"},
	{"city": "dali", "name": "整租·东岸润园 4室2厅 南", "district": "大理市", "street": "海东", "community": "东岸润园", "price": 1000, "square": 225.0, "direction": "南", "layout": "4室2厅3卫"},
	{"city": "dali", "name": "整租·东岸桂园小区 3室2厅 南/北", "district": "大理市", "street": "海东", "community": "东岸桂园小区", "price": 600, "square": 132.0, "direction": "南 北", "layout": "3室2厅2卫"},
	{"city": "dali", "name": "整租·东岸清园 1室1厅 南", "district": "大理市", "street": "海东", "community": "东岸清园", "price": 1000, "square": 54.0, "direction": "南", "layout": "1室1厅1卫"},
	{"city": "dali", "name": "整租·梦云南海东方 6室1厅 东", "district": "大理市", "street": "海东", "community": "梦云南海东方", "price": 46000, "square": 300.0, "direction": "东", "layout": "6室1厅6卫"},
	{"city": "dali", "name": "整租·梦云南海东方 6室2厅 西南", "district": "大理市", "street": "海东", "community": "梦云南海东方", "price": 8400, "square": 223.0, "direction": "西南", "layout": "6室2厅6卫"},
	{"city": "dali", "name": "整租·梦云南海东方 4室2厅 跃层 西", "district": "大理市", "street": "海东", "community": "梦云南海东方", "price": 10000, "square": 230.0, "direction": "西", "layout": "4室2厅4卫"},
	{"city": "dali", "name": "整租·东岸和园 3室2厅 南/北", "district": "大理市", "street": "海东", "community": "东岸和园", "price": 1500, "square": 131.0, "direction": "南 北", "layout": "3室2厅2卫"},
	{"city": "dali", "name": "整租·东岸桂园小区 3室1厅 南/北", "district": "大理市", "street": "海东", "community": "东岸桂园小区", "price": 1800, "square": 132.09, "direction": "南 北", "layout": "3室1厅2卫"},
	{"city": "dali", "name": "整租·东岸清园 1室2厅 西南", "district": "大理市", "street": "海东", "community": "东岸清园", "price": 1000, "square": 54.0, "direction": "西南", "layout": "1室2厅1卫"},
	{"city": "dali", "name": "整租·梦云南海东方 4室2厅 东/南/西", "district": "大理市", "street": "海东", "community": "梦云南海东方", "price": 10000, "square": 186.0, "direction": "东 南 西", "layout": "4室2厅3卫"},
	{"city": "dali", "name": "整租·纳思海岸春天 2室1厅 南/北", "district": "大理市", "street": "海东", "community": "纳思海岸春天", "price": 1300, "square": 69.84, "direction": "南 北", "layout": "2室1厅1卫"},
	{"city": "dali", "name": "整租·东岸清园 2室1厅 西", "district": "大理市", "street": "海东", "community": "东岸清园", "price": 1200, "square": 59.0, "direction": "西", "layout": "2室1厅1卫"},
	{"city": "dali", "name": "整租·东岸清园 2室1厅 东南", "district": "大理市", "street": "海东", "community": "东岸清园", "price": 1400, "square": 62.0, "direction": "东南", "layout": "2室1厅1卫"},
	{"city": "dali", "name": "整租·梦云南海东方 3室2厅 东/西", "district": "大理市", "street": "海东", "community": "梦云南海东方", "price": 11000, "square": 138.0, "direction": "东 西", "layout": "3室2厅2卫"},
	{"city": "dali", "name": "整租·梦云南海东方 3室2厅 西", "district": "大理市", "street": "海东", "community": "梦云南海东方", "price": 13500, "square": 180.0, "direction": "西", "layout": "3室2厅3卫"},
	{"city": "dali", "name": "整租·东岸清园 2室1厅 南", "district": "大理市", "street": "海东", "community": "东岸清园", "price": 1000, "square": 59.02, "direction": "南", "layout": "2室1厅1卫"},
	{"city": "dali", "name": "整租·梦云南海东方 4室1厅 西", "district": "大理市", "street": "海东", "community": "梦云南海东方", "price": 12000, "square": 198.0, "direction": "西", "layout": "4室1厅3卫"},
	{"city": "dali", "name": "整租·梦云南海东方 6室2厅 西南", "district": "大理市", "street": "海东", "community": "梦云南海东方", "price": 25000, "square": 300.0, "direction": "西南", "layout": "6室2厅6卫"},
	{"city": "dali", "name": "整租·梦云南海东方 5室3厅 东/南/西", "district": "大理市", "street": "海东", "community": "梦云南海东方", "price": 25000, "square": 300.0, "direction": "东 南 西", "layout": "5室3厅4卫"},
	{"city": "dali", "name": "整租·钜融城左岸高地 3室1厅 东/西", "district": "大理市", "street": "古城", "community": "钜融城左岸高地", "price": 7000, "square": 130.0, "direction": "东 西", "layout": "3室1厅2卫"},
	{"city": "dali", "name": "整租·大理的小院子南区 3室3厅 南/北", "district": "大理市", "street": "古城", "community": "大理的小院子南区", "price": 5800, "square": 208.0, "direction": "南 北", "layout": "3室3厅4卫"},
	{"city": "dali", "name": "整租·大理国际艺术家园区 4室2厅 东/西", "district": "大理市", "street": "古城", "community": "大理国际艺术家园区", "price": 8000, "square": 260.0, "direction": "东 西", "layout": "4室2厅3卫"},
	{"city": "dali", "name": "整租·教师民族住宅小区 6室3厅 南/北", "district": "大理市", "street": "古城", "community": "教师民族住宅小区", "price": 11000, "square": 400.0, "direction": "南 北", "layout": "6室3厅4卫"},
	{"city": "dali", "name": "整租·大理的小院子南区 4室2厅 东", "district": "大理市", "street": "古城", "community": "大理的小院子南区", "price": 12000, "square": 168.0, "direction": "东", "layout": "4室2厅4卫"},
	{"city": "dali", "name": "整租·博南巷 6室2厅 西", "district": "大理市", "street": "古城", "community": "博南巷", "price": 6800, "square": 230.0, "direction": "西", "layout": "6室2厅3卫"},
	{"city": "dali", "name": "整租·北罗久邑村 8室4厅 东/南", "district": "大理市", "street": "古城", "community": "北罗久邑村", "price": 14000, "square": 400.0, "direction": "东 南", "layout": "8室4厅5卫"},
	{"city": "dali", "name": "整租·大理南曼陀宫-垒翠园-鹤谐苑 5室2厅 复式 东/西", "district": "大理市", "street": "古城", "community": "大理南曼陀宫-垒翠园-鹤谐苑", "price": 7800, "square": 415.0, "direction": "东 西", "layout": "5室2厅5卫"},
	{"city": "dali", "name": "整租·大理的小院子北区 2室2厅 东南", "district": "大理市", "street": "古城", "community": "大理的小院子北区", "price": 5500, "square": 99.0, "direction": "东南", "layout": "2室2厅2卫"},
	{"city": "dali", "name": "整租·大理的小院子南区 1室2厅 南/北", "district": "大理市", "street": "古城", "community": "大理的小院子南区", "price": 3500, "square": 58.0, "direction": "南 北", "layout": "1室2厅1卫"},
	{"city": "dali", "name": "整租·耀鹏馨苑 4室2厅 南/北", "district": "大理市", "street": "古城", "community": "耀鹏馨苑", "price": 13000, "square": 260.0, "direction": "南 北", "layout": "4室2厅4卫"},
	{"city": "dali", "name": "整租·1806搬迁小镇 9室2厅 南/北", "district": "大理市", "street": "古城", "community": "1806搬迁小镇", "price": 6500, "square": 428.0, "direction": "南 北", "layout": "9室2厅7卫"},
	{"city": "dali", "name": "整租·钜融城左岸高地 3室1厅 东/西", "district": "大理市", "street": "古城", "community": "钜融城左岸高地", "price": 7000, "square": 130.0, "direction": "东 西", "layout": "3室1厅2卫"},
	{"city": "dali", "name": "整租·大理的小院子南区 3室3厅 南/北", "district": "大理市", "street": "古城", "community": "大理的小院子南区", "price": 5800, "square": 208.0, "direction": "南 北", "layout": "3室3厅4卫"},
	{"city": "dali", "name": "整租·大理国际艺术家园区 4室2厅 东/西", "district": "大理市", "street": "古城", "community": "大理国际艺术家园区", "price": 8000, "square": 260.0, "direction": "东 西", "layout": "4室2厅3卫"},
	{"city": "dali", "name": "整租·教师民族住宅小区 6室3厅 南/北", "district": "大理市", "street": "古城", "community": "教师民族住宅小区", "price": 11000, "square": 400.0, "direction": "南 北", "layout": "6室3厅4卫"},
	{"city": "dali", "name": "整租·大理的小院子南区 4室2厅 东", "district": "大理市", "street": "古城", "community": "大理的小院子南区", "price": 12000, "square": 168.0, "direction": "东", "layout": "4室2厅4卫"},
	{"city": "dali", "name": "整租·博南巷 6室2厅 西", "district": "大理市", "street": "古城", "community": "博南巷", "price": 6800, "square": 230.0, "direction": "西", "layout": "6室2厅3卫"},
	{"city": "dali", "name": "整租·北罗久邑村 8室4厅 东/南", "district": "大理市", "street": "古城", "community": "北罗久邑村", "price": 14000, "square": 400.0, "direction": "东 南", "layout": "8室4厅5卫"},
	{"city": "dali", "name": "整租·大理南曼陀宫-垒翠园-鹤谐苑 5室2厅 复式 东/西", "district": "大理市", "street": "古城", "community": "大理南曼陀宫-垒翠园-鹤谐苑", "price": 7800, "square": 415.0, "direction": "东 西", "layout": "5室2厅5卫"},
	{"city": "dali", "name": "整租·大理慢谷-世界健康小镇 1室1厅 南", "district": "大理市", "street": "凤仪", "community": "大理慢谷-世界健康小镇", "price": 900, "square": 53.0, "direction": "南", "layout": "1室1厅1卫"},
	{"city": "dali", "name": "整租·大理慢谷-世界健康小镇 3室2厅 南/北", "district": "大理市", "street": "凤仪", "community": "大理慢谷-世界健康小镇", "price": 2500, "square": 87.0, "direction": "南 北", "layout": "3室2厅1卫"},
	{"city": "dali", "name": "整租·大理慢谷-世界健康小镇 3室2厅 南", "district": "大理市", "street": "凤仪", "community": "大理慢谷-世界健康小镇", "price": 2400, "square": 82.0, "direction": "南", "layout": "3室2厅2卫"},
	{"city": "dali", "name": "整租·凤仪庄园 2室2厅 南/北", "district": "大理市", "street": "凤仪", "community": "凤仪庄园", "price": 1450, "square": 77.0, "direction": "南 北", "layout": "2室2厅1卫"},
	{"city": "dali", "name": "整租·大理慢谷-世界健康小镇 2室2厅 东", "district": "大理市", "street": "凤仪", "community": "大理慢谷-世界健康小镇", "price": 1800, "square": 89.0, "direction": "东", "layout": "2室2厅1卫"},
	{"city": "dali", "name": "整租·凤庭苑 3室2厅 东/西", "district": "大理市", "street": "凤仪", "community": "凤庭苑", "price": 1300, "square": 104.85, "direction": "东 西", "layout": "3室2厅1卫"},
	{"city": "dali", "name": "整租·凤仪庄园 3室2厅 南/北", "district": "大理市", "street": "凤仪", "community": "凤仪庄园", "price": 1500, "square": 96.0, "direction": "南 北", "layout": "3室2厅1卫"},
	{"city": "dali", "name": "整租·大理慢谷-世界健康小镇 2室2厅 南/北", "district": "大理市", "street": "凤仪", "community": "大理慢谷-世界健康小镇", "price": 1800, "square": 95.39, "direction": "南 北", "layout": "2室2厅2卫"},
	{"city": "dali", "name": "整租·凤仪庄园 3室2厅 南/北", "district": "大理市", "street": "凤仪", "community": "凤仪庄园", "price": 1600, "square": 108.0, "direction": "南 北", "layout": "3室2厅2卫"},
	{"city": "dali", "name": "整租·凤仪庄园 2室2厅 南/北", "district": "大理市", "street": "凤仪", "community": "凤仪庄园", "price": 1200, "square": 76.0, "direction": "南 北", "layout": "2室2厅1卫"},
	{"city": "dali", "name": "整租·华洲龙康苑 4室2厅 西南", "district": "大理市", "street": "凤仪", "community": "华洲龙康苑", "price": 2300, "square": 129.0, "direction": "西南", "layout": "4室2厅2卫"},
	{"city": "dali", "name": "整租·凤仪庄园 2室2厅 南/北", "district": "大理市", "street": "凤仪", "community": "凤仪庄园", "price": 1200, "square": 76.0, "direction": "南 北", "layout": "2室2厅1卫"},
	{"city": "dali", "name": "整租·凤仪庄园 3室2厅 南/北", "district": "大理市", "street": "凤仪", "community": "凤仪庄园", "price": 1500, "square": 119.0, "direction": "南 北", "layout": "3室2厅2卫"},
	{"city": "dali", "name": "整租·大理慢谷-世界健康小镇 3室2厅 南/北", "district": "大理市", "street": "凤仪", "community": "大理慢谷-世界健康小镇", "price": 2800, "square": 87.0, "direction": "南 北", "layout": "3室2厅1卫"},
	{"city": "dali", "name": "整租·凤仪庄园 3室2厅 南", "district": "大理市", "street": "凤仪", "community": "凤仪庄园", "price": 1400, "square": 96.0, "direction": "南", "layout": "3室2厅1卫"},
	{"city": "dali", "name": "整租·大理慢谷-世界健康小镇 3室2厅 南/北", "district": "大理市", "street": "凤仪", "community": "大理慢谷-世界健康小镇", "price": 2000, "square": 87.0, "direction": "南 北", "layout": "3室2厅1卫"},
	{"city": "dali", "name": "整租·大理慢谷-世界健康小镇 3室2厅 跃层 南/北", "district": "大理市", "street": "凤仪", "community": "大理慢谷-世界健康小镇", "price": 3000, "square": 81.03, "direction": "南 北", "layout": "3室2厅2卫"},
	{"city": "dali", "name": "整租·凤仪庄园 2室2厅 南", "district": "大理市", "street": "凤仪", "community": "凤仪庄园", "price": 1500, "square": 77.26, "direction": "南", "layout": "2室2厅1卫"},
	{"city": "dali", "name": "整租·大理慢谷-世界健康小镇 3室2厅 南", "district": "大理市", "street": "凤仪", "community": "大理慢谷-世界健康小镇", "price": 1700, "square": 87.0, "direction": "南", "layout": "3室2厅2卫"},
	{"city": "dali", "name": "整租·阳南南村 9室3厅 西南", "district": "大理市", "street": "下关北区", "community": "阳南南村", "price": 5416, "square": 460.0, "direction": "西南", "layout": "9室3厅3卫"},
	{"city": "dali", "name": "整租·大理华城海琴湾小区 5室4厅 东南/南", "district": "大理市", "street": "满江片区", "community": "大理华城海琴湾小区", "price": 2500, "square": 197.0, "direction": "东南 南", "layout": "5室4厅2卫"},
	{"city": "dali", "name": "整租·东岸泽园 3室2厅 东南", "district": "大理市", "street": "海东", "community": "东岸泽园", "price": 2000, "square": 136.88, "direction": "东南", "layout": "3室2厅2卫"},
	{"city": "dali", "name": "整租·大理的小院子北区 2室2厅 东南", "district": "大理市", "street": "古城", "community": "大理的小院子北区", "price": 5500, "square": 99.0, "direction": "东南", "layout": "2室2厅2卫"},
	{"city": "dali", "name": "整租·大理的小院子南区 1室2厅 南/北", "district": "大理市", "street": "古城", "community": "大理的小院子南区", "price": 3500, "square": 58.0, "direction": "南 北", "layout": "1室2厅1卫"},
	{"city": "dali", "name": "整租·耀鹏馨苑 4室2厅 南/北", "district": "大理市", "street": "古城", "community": "耀鹏馨苑", "price": 13000, "square": 260.0, "direction": "南 北", "layout": "4室2厅4卫"},
	{"city": "dali", "name": "整租·凤仪庄园 3室2厅 南/北", "district": "大理市", "street": "凤仪", "community": "凤仪庄园", "price": 2000, "square": 120.0, "direction": "南 北", "layout": "3室2厅2卫"},
	{"city": "dali", "name": "整租·凤仪庄园 3室2厅 南", "district": "大理市", "street": "凤仪", "community": "凤仪庄园", "price": 1600, "square": 96.0, "direction": "南", "layout": "3室2厅1卫"},
	{"city": "dali", "name": "整租·凤仪庄园 3室2厅 南", "district": "大理市", "street": "凤仪", "community": "凤仪庄园", "price": 1600, "square": 109.0, "direction": "南", "layout": "3室2厅2卫"},
	{"city": "dali", "name": "整租·万科·大理·拾叁月 4室2厅 南", "district": "大理市", "street": "满江片区", "community": "万科·大理·拾叁月", "price": 3800, "square": 143.0, "direction": "南", "layout": "4室2厅2卫"},
	{"city": "dali", "name": "整租·南五里桥 7室1厅 南", "district": "大理市", "street": "古城", "community": "南五里桥", "price": 6000, "square": 200.0, "direction": "南", "layout": "7室1厅8卫"},
	{"city": "dali", "name": "整租·大理的小院子北区 2室1厅 西", "district": "大理市", "street": "古城", "community": "大理的小院子北区", "price": 8000, "square": 65.21, "direction": "西", "layout": "2室1厅1卫"},
	{"city": "dali", "name": "整租·兴泰小区西区 4室2厅 南/北", "district": "大理市", "street": "下关北区", "community": "兴泰小区西区", "price": 2000, "square": 123.0, "direction": "南 北", "layout": "4室2厅2卫"},
	{"city": "dali", "name": "整租·华辰玉海豪庭 3室2厅 南", "district": "大理市", "street": "下关北区", "community": "华辰玉海豪庭", "price": 2200, "square": 124.0, "direction": "南", "layout": "3室2厅2卫"},
	{"city": "dali", "name": "整租·大理的小院子南区 3室1厅 跃层 东/东南/西", "district": "大理市", "street": "古城", "community": "大理的小院子南区", "price": 10000, "square": 179.89, "direction": "东 东南 西", "layout": "3室1厅4卫"},
	{"city": "dali", "name": "整租·大理的小院子南区 4室2厅 东/西", "district": "大理市", "street": "古城", "community": "大理的小院子南区", "price": 7500, "square": 156.0, "direction": "东 西", "layout": "4室2厅4卫"},
	{"city": "dali", "name": "整租·文献路 6室3厅 南/北", "district": "大理市", "street": "古城", "community": "文献路", "price": 10000, "square": 350.0, "direction": "南 北", "layout": "6室3厅5卫"},
	{"city": "dali", "name": "整租·汇宁豪品 3室2厅 西", "district": "大理市", "street": "下关北区", "community": "汇宁豪品", "price": 2500, "square": 105.0, "direction": "西", "layout": "3室2厅1卫"},
	{"city": "dali", "name": "整租·大理的小院子中区 3室1厅 东/西", "district": "大理市", "street": "古城", "community": "大理的小院子中区", "price": 6500, "square": 119.27, "direction": "东 西", "layout": "3室1厅3卫"},
	{"city": "dali", "name": "整租·俊发滨海俊园 1室1厅 南/北", "district": "大理市", "street": "市区", "community": "俊发滨海俊园", "price": 1800, "square": 51.0, "direction": "南 北", "layout": "1室1厅2卫"},
	{"city": "dali", "name": "整租·大理公馆 2室2厅 西北", "district": "大理市", "street": "满江片区", "community": "大理公馆", "price": 3200, "square": 89.0, "direction": "西北", "layout": "2室2厅1卫"},
	{"city": "dali", "name": "整租·俊发滨海俊园 5室2厅 南/北", "district": "大理市", "street": "市区", "community": "俊发滨海俊园", "price": 9000, "square": 313.0, "direction": "南 北", "layout": "5室2厅4卫"},
	{"city": "dali", "name": "整租·五交化东大院 3室2厅 东/西", "district": "大理市", "street": "下关北区", "community": "五交化东大院", "price": 1200, "square": 89.2, "direction": "东 西", "layout": "3室2厅1卫"},
	{"city": "dali", "name": "整租·观天下 3室2厅 南", "district": "大理市", "street": "经开区", "community": "观天下", "price": 1500, "square": 113.0, "direction": "南", "layout": "3室2厅2卫"},
	{"city": "dali", "name": "整租·龙悦华府 3室2厅 南/北", "district": "大理市", "street": "下关北区", "community": "龙悦华府", "price": 3000, "square": 143.0, "direction": "南 北", "layout": "3室2厅2卫"},
	{"city": "dali", "name": "整租·耀鹏明珠 5室2厅 东/西", "district": "大理市", "street": "经开区", "community": "耀鹏明珠", "price": 6800, "square": 281.88, "direction": "东 西", "layout": "5室2厅1卫"},
	{"city": "dali", "name": "整租·河畔阳光 2室2厅 复式 南", "district": "大理市", "street": "下关北区", "community": "河畔阳光", "price": 2200, "square": 70.0, "direction": "南", "layout": "2室2厅1卫"},
	{"city": "dali", "name": "整租·钜融城左岸高地 4室2厅 复式 东/西", "district": "大理市", "street": "古城", "community": "钜融城左岸高地", "price": 5500, "square": 162.0, "direction": "东 西", "layout": "4室2厅2卫"},
	{"city": "dali", "name": "整租·钜融城左岸高地 5室2厅 东/西", "district": "大理市", "street": "古城", "community": "钜融城左岸高地", "price": 5500, "square": 217.0, "direction": "东 西", "layout": "5室2厅4卫"},
	{"city": "dali", "name": "整租·钜融城左岸高地 3室3厅 南/北", "district": "大理市", "street": "古城", "community": "钜融城左岸高地", "price": 3800, "square": 330.0, "direction": "南 北", "layout": "3室3厅5卫"},
	{"city": "dali", "name": "整租·五洲国际商贸城A区 1室0厅 北", "district": "大理市", "street": "满江片区", "community": "五洲国际商贸城A区", "price": 550, "square": 35.0, "direction": "北", "layout": "1室0厅1卫"},
	{"city": "dali", "name": "整租·万科·大理·拾叁月 3室2厅 西", "district": "大理市", "street": "满江片区", "community": "万科·大理·拾叁月", "price": 5500, "square": 133.0, "direction": "西", "layout": "3室2厅2卫"},
	{"city": "dali", "name": "整租·凤仪供电所宿舍 3室2厅 东/西", "district": "大理市", "street": "凤仪", "community": "凤仪供电所宿舍", "price": 1400, "square": 99.94, "direction": "东 西", "layout": "3室2厅1卫"},
	{"city": "dali", "name": "整租·大理朴墅 3室2厅 东/西", "district": "大理市", "street": "古城", "community": "大理朴墅", "price": 8000, "square": 137.0, "direction": "东 西", "layout": "3室2厅4卫"},
	{"city": "dali", "name": "整租·万科·大理·拾叁月 2室2厅 东南", "district": "大理市", "street": "满江片区", "community": "万科·大理·拾叁月", "price": 2500, "square": 86.0, "direction": "东南", "layout": "2室2厅1卫"},
	{"city": "dali", "name": "整租·大理的小院子南区 4室2厅 东", "district": "大理市", "street": "古城", "community": "大理的小院子南区", "price": 5000, "square": 220.0, "direction": "东", "layout": "4室2厅3卫"},
	{"city": "dali", "name": "整租·云麓青城 3室2厅 东", "district": "大理市", "street": "满江片区", "community": "云麓青城", "price": 2200, "square": 119.0, "direction": "东", "layout": "3室2厅2卫"},
	{"city": "dali", "name": "整租·天泰大理十畝 3室2厅 跃层 东", "district": "大理市", "street": "市区", "community": "天泰大理十畝", "price": 4600, "square": 86.0, "direction": "东", "layout": "3室2厅2卫"},
	{"city": "dali", "name": "整租·大理国际艺术家园区 4室2厅 东/西/北", "district": "大理市", "street": "古城", "community": "大理国际艺术家园区", "price": 10000, "square": 257.0, "direction": "东 西 北", "layout": "4室2厅2卫"}
]